healthchecker/__init__.py
healthchecker/__main__.py
healthchecker/core.py
healthchecker/objects.py
healthchecker/settings.py
healthchecker/tests/__init__.py
healthchecker/tests/tests_cli.py
healthchecker/tests/tests_core.py
healthchecker/tests/tests_main.py
healthchecker/tests/tests_objects.py
healthchecker/tests/tests_utils.py
healthchecker/utils.py
healthchecker-1.1.1.dist-info/entry_points.txt
healthchecker-1.1.1.dist-info/LICENSE
healthchecker-1.1.1.dist-info/WHEEL
healthchecker-1.1.1.dist-info/METADATA
healthchecker-1.1.1.dist-info/RECORD
