Metadata-Version: 2.1
Name: healthchecker
Version: 1.1.1
Summary: Check sites health and publish results in a file in Github, filesystem or an API
Home-page: https://gitlab.com/rlyehlab/healthchecker
License: GPL-3.0+
Author: HacKan
Author-email: hackan@rlab.be
Requires-Python: >=3.7,<4.0
Classifier: Development Status :: 5 - Production/Stable
Classifier: Environment :: Console
Classifier: Intended Audience :: Developers
Classifier: Intended Audience :: System Administrators
Classifier: License :: OSI Approved :: GNU General Public License v3 or later (GPLv3+)
Classifier: Natural Language :: English
Classifier: Operating System :: POSIX :: Linux
Classifier: Programming Language :: Python :: 3
Classifier: Programming Language :: Python :: 3 :: Only
Classifier: Programming Language :: Python :: 3.7
Classifier: Programming Language :: Python :: 3.8
Classifier: Topic :: System :: Monitoring
Classifier: Topic :: Utilities
Classifier: Typing :: Typed
Requires-Dist: PyGithub (>=1.44.1,<2.0.0)
Requires-Dist: requests (>=2.22.0,<3.0.0)
Project-URL: Repository, https://gitlab.com/rlyehlab/healthchecker
